[{"keyword":"Feature","type":"feature","description":"","line":3,"name":"Team page - all functionalities","uri":"C:\\Projekti\\Teams_Wdio\\features\\team_page.feature","tags":[{"location":{"line":1,"column":1},"name":"@notNewUser","id":"780edfba-9d45-4fce-bf9e-c76e54bf4f9c"},{"location":{"line":2,"column":1},"name":"@permanentAdmin","id":"504b0678-dbfa-492d-a737-9aa1d17fe2dd"}],"elements":[{"keyword":"Scenario","type":"scenario","description":"","name":"Check team members data","tags":[{"name":"@notNewUser","astNodeId":"780edfba-9d45-4fce-bf9e-c76e54bf4f9c"},{"name":"@permanentAdmin","astNodeId":"504b0678-dbfa-492d-a737-9aa1d17fe2dd"}],"id":"team-page---all-functionalitiescheck-team-members-data","steps":[{"arguments":[],"keyword":"Before","name":"","result":{"status":"passed","duration":1000000},"line":null,"match":{"location":"can not be determined with webdriver.io"}},{"arguments":[],"keyword":"When","name":"I click on Team label","result":{"status":"passed","duration":1132000000},"line":null,"match":{"location":"can not be determined with webdriver.io"}},{"arguments":[],"keyword":"After","name":"","result":{"status":"passed","duration":1000000},"line":null,"match":{"location":"can not be determined with webdriver.io"}}]}],"id":"team-page---all-functionalities","metadata":{"browser":{"name":"chrome","version":"140.0.7339.128"},"device":"Device name not known","platform":{"name":"windows","version":"Version not known"}}}]
